vipickle/__init__.py
vipickle/_version.py
vipickle/errors.py
vipickle/mixin.py
vipickle/save_utils.py
vipickle-0.1.0.dist-info/METADATA
vipickle-0.1.0.dist-info/WHEEL
vipickle-0.1.0.dist-info/top_level.txt
vipickle-0.1.0.dist-info/RECORD
