Metadata-Version: 2.1
Name: vipickle
Version: 0.1.0
Summary: vipickle is a tiny python package for saving instances with unpickable attributes
Author-email: Hakim Cheikh <hakimcheikh@yahoo.fr>
Project-URL: homepage, https://github.com/h4c5/vipickle
Project-URL: documentation, https://h4c5.github.io/vipickle
Project-URL: repository, https://github.com/h4c5/vipickle
Project-URL: Bug Tracker, https://github.com/h4c5/vipickle/issues
Classifier: Operating System :: OS Independent
Classifier: Programming Language :: Python
Classifier: Programming Language :: Python :: 3.8
Classifier: Programming Language :: Python :: 3.9
Classifier: Programming Language :: Python :: 3.10
Classifier: Programming Language :: Python :: 3.11
Requires-Python: <4.0,>=3.8
Requires-Dist: loguru
Requires-Dist: orjson
Provides-Extra: dev
Requires-Dist: black ; extra == 'dev'
Requires-Dist: ruff ; extra == 'dev'
Requires-Dist: bandit[toml] ; extra == 'dev'
Requires-Dist: pytest (>=7.0) ; extra == 'dev'
Requires-Dist: pytest-cov (>=3.0) ; extra == 'dev'
Requires-Dist: pytest-datadir (>=1.0) ; extra == 'dev'
Requires-Dist: numpy ; extra == 'dev'
Provides-Extra: doc
Requires-Dist: mkdocs-material (>=8.0) ; extra == 'doc'
Requires-Dist: mkdocstrings[python] ; extra == 'doc'
Requires-Dist: mkdocs-gen-files ; extra == 'doc'
Requires-Dist: mkdocs-literate-nav ; extra == 'doc'
Requires-Dist: mkdocs-section-index ; extra == 'doc'
Provides-Extra: test
Requires-Dist: pytest (>=7.0) ; extra == 'test'
Requires-Dist: pytest-cov (>=3.0) ; extra == 'test'
Requires-Dist: pytest-datadir (>=1.0) ; extra == 'test'
Requires-Dist: nox (>=2022) ; extra == 'test'
Requires-Dist: numpy ; extra == 'test'
